cacheml/__init__.py
cacheml/cache.py
cacheml/cml.py
cacheml/crypto.py
CacheML-1.0.4.dist-info/LICENSE.txt
CacheML-1.0.4.dist-info/METADATA
CacheML-1.0.4.dist-info/WHEEL
CacheML-1.0.4.dist-info/top_level.txt
CacheML-1.0.4.dist-info/RECORD
