Metadata-Version: 2.1
Name: CacheML
Version: 1.0.4
Summary: Cache ML -- layer on top of joblib to cache parsed datasets, dramatically reducing load time of large data files. Also supports encryption at rest.
Home-page: https://github.com/BenedatLLC/CacheML
Author: Benedat LLC
Author-email: jeff.fischer@benedat.com
License: UNKNOWN
Platform: UNKNOWN
Classifier: Programming Language :: Python :: 3 :: Only
Classifier: Development Status :: 4 - Beta
Classifier: License :: OSI Approved :: Apache Software License
Classifier: Operating System :: OS Independent
Classifier: Topic :: Utilities
Classifier: Topic :: Scientific/Engineering :: Information Analysis
Requires-Python: >=3.6
License-File: LICENSE.txt
Requires-Dist: joblib
Requires-Dist: s3fs
Requires-Dist: pycryptodome
Requires-Dist: click
